LICENSE
MANIFEST.in
README.rst
setup.py
bin/ludolph
init.d/ludolph.conf
init.d/ludolph.debian
init.d/ludolph.redhat
init.d/ludolph.service
init.d/ludolph.xml
ludolph/__init__.py
ludolph/bot.py
ludolph/command.py
ludolph/cron.py
ludolph/db.py
ludolph/ludolph.cfg.example
ludolph/main.py
ludolph/message.py
ludolph/utils.py
ludolph/web.py
ludolph.egg-info/PKG-INFO
ludolph.egg-info/SOURCES.txt
ludolph.egg-info/dependency_links.txt
ludolph.egg-info/requires.txt
ludolph.egg-info/top_level.txt
ludolph/plugins/__init__.py
ludolph/plugins/base.py
ludolph/plugins/commands.py
ludolph/plugins/muc.py
ludolph/plugins/plugin.py
ludolph/plugins/avatars/erigones.png
ludolph/plugins/avatars/face1.png
ludolph/plugins/avatars/face10.png
ludolph/plugins/avatars/face11.png
ludolph/plugins/avatars/face12.png
ludolph/plugins/avatars/face13.png
ludolph/plugins/avatars/face14.png
ludolph/plugins/avatars/face15.png
ludolph/plugins/avatars/face16.png
ludolph/plugins/avatars/face2.png
ludolph/plugins/avatars/face3.png
ludolph/plugins/avatars/face4.png
ludolph/plugins/avatars/face5.png
ludolph/plugins/avatars/face6.png
ludolph/plugins/avatars/face7.png
ludolph/plugins/avatars/face8.png
ludolph/plugins/avatars/face9.png
ludolph/plugins/avatars/ludolph.png
ludolph/tests/__init__.py
ludolph/tests/fake_bot.py
ludolph/tests/test_commands.py
ludolph/tests/test_ludolph_plugin.py