Metadata-Version: 1.1
Name: ludolph
Version: 0.9.2
Summary: Monitoring Jabber Bot
Home-page: https://github.com/erigones/Ludolph/
Author: Erigones
Author-email: erigones [at] erigones.com
License: BSD
Platform: any
Classifier: Environment :: Console
Classifier: Intended Audience :: System Administrators
Classifier: Intended Audience :: Developers
Classifier: Operating System :: Unix
Classifier: Operating System :: POSIX :: Linux
Classifier: License :: OSI Approved :: BSD License
Classifier: Programming Language :: Python
Classifier: Programming Language :: Python :: 2
Classifier: Programming Language :: Python :: 3
Classifier: Development Status :: 5 - Production/Stable
Classifier: Topic :: Communications :: Chat
Classifier: Topic :: Utilities
